{
  "$schema": "https://mintlify.com/docs.json",
  "theme": "mint",
  "name": "deBridge Messaging Protocol",
  "colors": {
    "primary": "#16A34A",
    "light": "#07C983",
    "dark": "#15803D"
  },
  "favicon": "/favicon.ico",
  "navigation": {
    "tabs": [
      {
        "tab": "deBridge Messaging Protocol",
        "groups": [
          {
            "group": "Overview",
            "pages": [
              "dmp/protocol-overview",
              "dmp/fees-supported-chains",
              "dmp/deployed-contracts",
              "dmp/security",
              "dmp/slashing-and-delegated-staking"
            ]
          },
          {
            "group": "Dev Guides",
            "pages": [
              "dev-guides/cross-chain-call-lifecycle",
              "dev-guides/development-tools",
              "dev-guides/gathering-data-for-claim"
            ]
          }
        ]
      },
      {
        "tab": "EVM",
        "groups": [
          {
            "group": "Examples",
            "pages": [
              "dev-guides/evm/building-evm-dapp"
            ]
          },
          {
            "group": "Interfaces",
            "pages": [
              "dev-guides/evm/interfaces/ICallProxy",
              "dev-guides/evm/interfaces/IDeBridgeGate",
              "dev-guides/evm/interfaces/IDeBridgeToken",
              "dev-guides/evm/interfaces/IDeBridgeTokenDeployer",
              "dev-guides/evm/interfaces/IOraclesManager",
              "dev-guides/evm/interfaces/ISignatureVerifier",
              "dev-guides/evm/interfaces/IWethGate"
            ]
          },
          {
            "group": "Libraries",
            "pages": [
              "dev-guides/evm/libraries/flags"
            ]
          },
          {
            "group": "Periphery",
            "pages": [
              "dev-guides/evm/periphery/CallProxy",
              "dev-guides/evm/periphery/DeBridgeToken",
              "dev-guides/evm/periphery/DeBridgeTokenProxy",
              "dev-guides/evm/periphery/SimpleFeeProxy"
            ]
          },
          {
            "group": "Transfers",
            "pages": [
              "dev-guides/evm/transfers/DeBridgeGate",
              "dev-guides/evm/transfers/DeBridgeTokenDeployer",
              "dev-guides/evm/transfers/OraclesManager",
              "dev-guides/evm/transfers/SignatureVerifier",
              "dev-guides/evm/transfers/WethGate"
            ]
          }
        ]
      },
      {
        "tab": "Solana",
        "groups": [
          {
            "group": "Cross-Chain Calls",
            "pages": [
              "dev-guides/solana/sending-cross-chain-messages",
              "dev-guides/solana/on-chain-external-call-preparation",
              "dev-guides/solana/off-chain-external-call-preparation"
            ]
          }
        ]
      }
    ],
    "global": {
      "anchors": [
        {
          "anchor": "deBridge Home",
          "href": "https://acme-68677d63.mintlify.app/",
          "icon": "house"
        },
        {
          "anchor": "deBridge Messaging Protocol",
          "href": "https://acme-fc8786fa.mintlify.app/",
          "icon": "envelope"
        },
        {
          "anchor": "deBridge Liquidity Network",
          "href": "https://acme-1c46979f.mintlify.app/",
          "icon": "envelope-open-dollar"
        },
        {
          "anchor": "Community",
          "href": "https://mintlify.com/community",
          "icon": "discord"
        }
      ]
    }
  },
  "logo": {
    "light": "/logo/debridge-dark.svg",
    "dark": "/logo/debridge-dark.svg"
  },
  "navbar": {
    "links": [
      {
        "label": "Support",
        "href": "mailto:hi@mintlify.com"
      }
    ],
    "primary": {
      "type": "button",
      "label": "Dashboard",
      "href": "https://dashboard.mintlify.com"
    }
  },
  "footer": {
    "socials": {
      "x": "https://x.com/mintlify",
      "github": "https://github.com/mintlify",
      "linkedin": "https://linkedin.com/company/mintlify"
    }
  }
}